fffa/__init__.py
fffa/fff.py
fffa/main.py
fffa/update.py
fffa/utils.py
fffa-0.1.1.dist-info/licenses/LICENSE
fffa-0.1.1.dist-info/METADATA
fffa-0.1.1.dist-info/WHEEL
fffa-0.1.1.dist-info/top_level.txt
fffa-0.1.1.dist-info/RECORD
