Metadata-Version: 2.4
Name: fffa
Version: 0.1.1
Summary: FFFA: A Nature-Inspired Optimization Algorithm
Home-page: https://github.com/zeshanalvi/FFFA
Author: Zeshan Khan
Author-email: zeshankhanalvi@gmail.com 
Classifier: Programming Language :: Python :: 3
Classifier: License :: OSI Approved :: MIT License
Classifier: Operating System :: OS Independent
Requires-Python: >=3.7
License-File: LICENSE
Dynamic: author
Dynamic: author-email
Dynamic: classifier
Dynamic: description
Dynamic: description-content-type
Dynamic: home-page
Dynamic: license-file
Dynamic: requires-python
Dynamic: summary
